{
  "config": {
    "category": "asr",
    "model": "zipformer"
  },
  "default_variant": "default",
  "variants": {
    "default": {
      "archives": [
        {
          "path": "asr/model/zipformer/default/",
          "url": "https://github.com/k2-fsa/sherpa-onnx/releases/download/asr-models/sherpa-onnx-zipformer-zh-en-2023-11-22.tar.bz2",
          "sha256": null,
          "extract": [
            "encoder-epoch-34-avg-19.onnx",
            "decoder-epoch-34-avg-19.onnx",
            "joiner-epoch-34-avg-19.onnx",
            "tokens.txt"
          ]
        }
      ]
    }
  }
}
